<annotation>
	<folder>tanker</folder>
	<filename>tanker_11.jpg</filename>
	<path>C:\Users\avp10\dataset_images\tanker\tanker_11.jpg</path>
	<source>
		<database>Unknown</database>
	</source>
	<size>
		<width>640</width>
		<height>319</height>
		<depth>3</depth>
	</size>
	<segmented>0</segmented>
	<object>
		<name>tanker</name>
		<pose>Unspecified</pose>
		<truncated>0</truncated>
		<difficult>0</difficult>
		<bndbox>
			<xmin>223</xmin>
			<ymin>30</ymin>
			<xmax>414</xmax>
			<ymax>132</ymax>
		</bndbox>
	</object>
	<object>
		<name>tug_boat</name>
		<pose>Unspecified</pose>
		<truncated>0</truncated>
		<difficult>0</difficult>
		<bndbox>
			<xmin>168</xmin>
			<ymin>92</ymin>
			<xmax>213</xmax>
			<ymax>133</ymax>
		</bndbox>
	</object>
	<object>
		<name>tug_boat</name>
		<pose>Unspecified</pose>
		<truncated>0</truncated>
		<difficult>0</difficult>
		<bndbox>
			<xmin>407</xmin>
			<ymin>89</ymin>
			<xmax>456</xmax>
			<ymax>134</ymax>
		</bndbox>
	</object>
	<object>
		<name>boat</name>
		<pose>Unspecified</pose>
		<truncated>0</truncated>
		<difficult>0</difficult>
		<bndbox>
			<xmin>250</xmin>
			<ymin>130</ymin>
			<xmax>338</xmax>
			<ymax>167</ymax>
		</bndbox>
	</object>
</annotation>
