<annotation>
	<folder>tanker</folder>
	<filename>tanker_85.jpg</filename>
	<path>C:\Users\avp10\dataset_images\tanker\tanker_85.jpg</path>
	<source>
		<database>Unknown</database>
	</source>
	<size>
		<width>640</width>
		<height>389</height>
		<depth>3</depth>
	</size>
	<segmented>0</segmented>
	<object>
		<name>tanker</name>
		<pose>Unspecified</pose>
		<truncated>0</truncated>
		<difficult>0</difficult>
		<bndbox>
			<xmin>198</xmin>
			<ymin>32</ymin>
			<xmax>571</xmax>
			<ymax>340</ymax>
		</bndbox>
	</object>
	<object>
		<name>tug_boat</name>
		<pose>Unspecified</pose>
		<truncated>0</truncated>
		<difficult>0</difficult>
		<bndbox>
			<xmin>31</xmin>
			<ymin>224</ymin>
			<xmax>188</xmax>
			<ymax>336</ymax>
		</bndbox>
	</object>
	<object>
		<name>tug_boat</name>
		<pose>Unspecified</pose>
		<truncated>0</truncated>
		<difficult>0</difficult>
		<bndbox>
			<xmin>308</xmin>
			<ymin>175</ymin>
			<xmax>450</xmax>
			<ymax>347</ymax>
		</bndbox>
	</object>
</annotation>
