<annotation>
	<folder>tug_boat</folder>
	<filename>tug_boat_68.jpg</filename>
	<path>C:\Users\avp10\dataset_images\tug_boat\tug_boat_68.jpg</path>
	<source>
		<database>Unknown</database>
	</source>
	<size>
		<width>640</width>
		<height>560</height>
		<depth>3</depth>
	</size>
	<segmented>0</segmented>
	<object>
		<name>tug_boat</name>
		<pose>Unspecified</pose>
		<truncated>0</truncated>
		<difficult>0</difficult>
		<bndbox>
			<xmin>126</xmin>
			<ymin>195</ymin>
			<xmax>553</xmax>
			<ymax>533</ymax>
		</bndbox>
	</object>
</annotation>
